divide/__init__.py
divide/divide_by_three.py
multiply/__init__.py
multiply/multiply_by_three.py
vivek_test_pkg-1.0.0.dist-info/LICENSE.txt
vivek_test_pkg-1.0.0.dist-info/METADATA
vivek_test_pkg-1.0.0.dist-info/WHEEL
vivek_test_pkg-1.0.0.dist-info/top_level.txt
vivek_test_pkg-1.0.0.dist-info/RECORD
